{
  "course_id": "old-testament-survey",
  "course_name": "Old Testament Survey",
  "slides": [
    {
      "id": 1,
      "title": "Title",
      "file": "slide_1_title.html"
    },
    {
      "id": 2,
      "title": "Course Overview",
      "file": "slide_2_course_overview.html"
    },
    {
      "id": 3,
      "title": "Course Structure",
      "file": "slide_3_course_structure.html"
    },
    {
      "id": 4,
      "title": "Learning Objectives",
      "file": "slide_4_learning_objectives.html"
    },
    {
      "id": 5,
      "title": "Call to Action",
      "file": "slide_5_call_to_action.html"
    }
  ],
  "voiceover": "intro-voiceover.wav",
  "created_at": "2026-01-09",
  "color_scheme": "professional-blue-gray-warm-earth",
  "status": "complete"
}
